lspopt/__init__.py
lspopt/__version__.py
lspopt/lsp.py
lspopt/utils.py
lspopt/data/__init__.py
lspopt/data/c.npy
lspopt/data/weights.npy
lspopt-1.3.0.dist-info/LICENSE
lspopt-1.3.0.dist-info/METADATA
lspopt-1.3.0.dist-info/WHEEL
lspopt-1.3.0.dist-info/top_level.txt
lspopt-1.3.0.dist-info/RECORD
